gower_exp/__init__.py
gower_exp/accelerators.py
gower_exp/core.py
gower_exp/gower_dist.py
gower_exp/parallel.py
gower_exp/sklearn_compat.py
gower_exp/topn.py
gower_exp/vectorized.py
gower_exp-0.1.4.dist-info/licenses/LICENSE
gower_exp-0.1.4.dist-info/METADATA
gower_exp-0.1.4.dist-info/WHEEL
gower_exp-0.1.4.dist-info/top_level.txt
gower_exp-0.1.4.dist-info/RECORD
