Metadata-Version: 2.4
Name: gower_exp
Version: 0.1.4
Summary: Production-ready Gower distance with modern Python tooling
Author: Charles Frenzel
License-Expression: MIT
Project-URL: Homepage, https://github.com/momonga-ml/gower-express
Project-URL: Bug Reports, https://github.com/momonga-ml/gower-express/issues
Project-URL: Source, https://github.com/momonga-ml/gower-express
Project-URL: Original, https://github.com/wwwjk366/gower
Keywords: gower,gower_exp,distance,matrix,similarity,clustering
Classifier: Development Status :: 3 - Alpha
Classifier: Intended Audience :: Developers
Classifier: Topic :: Scientific/Engineering :: Mathematics
Classifier: Programming Language :: Python :: 3
Classifier: Programming Language :: Python :: 3.11
Classifier: Programming Language :: Python :: 3.12
Classifier: Operating System :: OS Independent
Requires-Python: >=3.11
License-File: LICENSE
Requires-Dist: numpy
Requires-Dist: scipy
Requires-Dist: pandas
Requires-Dist: numba>=0.56.0
Requires-Dist: joblib>=1.2.0
Provides-Extra: dev
Requires-Dist: pytest; extra == "dev"
Requires-Dist: pytest-cov; extra == "dev"
Requires-Dist: ruff; extra == "dev"
Requires-Dist: pre-commit; extra == "dev"
Requires-Dist: bandit[toml]; extra == "dev"
Provides-Extra: gpu
Requires-Dist: cupy-cuda11x>=13.6.0; platform_system != "Darwin" and extra == "gpu"
Provides-Extra: sklearn
Requires-Dist: scikit-learn>=0.24.0; extra == "sklearn"
Dynamic: license-file
